bock/__init__.py
bock/cli.py
bock/commands/__init__.py
bock/commands/info.py
bock/commands/log.py
bock/commands/project.py
bock/commands/reset.py
bock/commands/start.py
bock/commands/status.py
bock/commands/stop.py
bock/commands/update.py
bock/service/GamsLocalDocker.py
bock/service/GamsLocalFileService.py
bock/service/__init__.py
bock/service/zimlab.py
bock/utils/__init__.py
bock/utils/wsl.py
bock-0.2.0.dist-info/LICENSE
bock-0.2.0.dist-info/METADATA
bock-0.2.0.dist-info/WHEEL
bock-0.2.0.dist-info/entry_points.txt
bock-0.2.0.dist-info/top_level.txt
bock-0.2.0.dist-info/RECORD
