Metadata-Version: 2.1
Name: bock
Version: 0.2.0
Summary: Small cli - tool to support GAMS4+ local development
Author: Sebastian Stoff
Author-email: SebastianStoff@gmx.at
License: UNKNOWN
Platform: UNKNOWN
Classifier: Development Status :: 3 - Alpha
Classifier: Intended Audience :: Developers
Classifier: Topic :: Software Development :: Build Tools
Classifier: License :: OSI Approved :: MIT License
Classifier: Programming Language :: Python :: 3.10
Requires-Python: >=3
License-File: LICENSE
Requires-Dist: autopep8 (==1.6.0)
Requires-Dist: bleach (==4.1.0)
Requires-Dist: build (==0.7.0)
Requires-Dist: certifi (==2021.10.8)
Requires-Dist: charset-normalizer (==2.0.7)
Requires-Dist: click (==8.0.3)
Requires-Dist: colorama (==0.4.4)
Requires-Dist: docutils (==0.18)
Requires-Dist: idna (==3.3)
Requires-Dist: importlib-metadata (==4.8.1)
Requires-Dist: keyring (==23.2.1)
Requires-Dist: packaging (==21.2)
Requires-Dist: pep517 (==0.12.0)
Requires-Dist: pkginfo (==1.7.1)
Requires-Dist: pycodestyle (==2.8.0)
Requires-Dist: Pygments (==2.10.0)
Requires-Dist: pyparsing (==2.4.7)
Requires-Dist: pywin32-ctypes (==0.2.0)
Requires-Dist: readme-renderer (==30.0)
Requires-Dist: requests (==2.26.0)
Requires-Dist: requests-toolbelt (==0.9.1)
Requires-Dist: rfc3986 (==1.5.0)
Requires-Dist: six (==1.16.0)
Requires-Dist: toml (==0.10.2)
Requires-Dist: tomli (==1.2.2)
Requires-Dist: tqdm (==4.62.3)
Requires-Dist: twine (==3.4.2)
Requires-Dist: urllib3 (==1.26.7)
Requires-Dist: webencodings (==0.5.1)
Requires-Dist: zipp (==3.6.0)
